spatialexperiment/__init__.py
spatialexperiment/_combineutils.py
spatialexperiment/_imgutils.py
spatialexperiment/_initutils.py
spatialexperiment/_validators.py
spatialexperiment/spatialexperiment.py
spatialexperiment/spatialimage.py
spatialexperiment/io/__init__.py
spatialexperiment/io/tenx_visium.py
spatialexperiment-0.1.0.dist-info/licenses/LICENSE.txt
spatialexperiment-0.1.0.dist-info/METADATA
spatialexperiment-0.1.0.dist-info/WHEEL
spatialexperiment-0.1.0.dist-info/top_level.txt
spatialexperiment-0.1.0.dist-info/RECORD
