Metadata-Version: 2.4
Name: SpatialExperiment
Version: 0.1.0
Summary: Container class for storing data from spatial-omics experiments
Home-page: https://github.com/biocpy/spatialexperiment
Author: keviny2
Author-email: kevinyang10@gmail.com
License: MIT
Project-URL: Documentation, https://github.com/biocpy/spatialexperiment
Project-URL: Source, https://github.com/biocpy/spatialexperiment
Platform: any
Classifier: Development Status :: 4 - Beta
Classifier: Programming Language :: Python
Requires-Python: >=3.9
License-File: LICENSE.txt
Requires-Dist: importlib-metadata; python_version < "3.8"
Requires-Dist: biocframe>=0.7.2
Requires-Dist: biocutils>=0.3.3
Requires-Dist: singlecellexperiment>=0.6.0
Requires-Dist: pillow>=11.0
Requires-Dist: requests
Requires-Dist: scipy~=1.13
Requires-Dist: rasterio
Provides-Extra: optional
Requires-Dist: pandas; extra == "optional"
Requires-Dist: anndata; extra == "optional"
Requires-Dist: delayedarray; extra == "optional"
Provides-Extra: testing
Requires-Dist: setuptools; extra == "testing"
Requires-Dist: pytest; extra == "testing"
Requires-Dist: pytest-cov; extra == "testing"
Requires-Dist: pandas; extra == "testing"
Requires-Dist: anndata; extra == "testing"
Requires-Dist: delayedarray; extra == "testing"
Dynamic: license-file
